fanstatic/__init__.py
fanstatic/checksum.py
fanstatic/compiler.py
fanstatic/config.py
fanstatic/core.py
fanstatic/inclusion.py
fanstatic/injector.py
fanstatic/publisher.py
fanstatic/registry.py
fanstatic/wsgi.py
fanstatic/tests/__init__.py
fanstatic/tests/conftest.py
fanstatic/tests/test_bundle.py
fanstatic/tests/test_checksum.py
fanstatic/tests/test_compiler.py
fanstatic/tests/test_config.py
fanstatic/tests/test_core.py
fanstatic/tests/test_injector.py
fanstatic/tests/test_injectorplugin.py
fanstatic/tests/test_publisher.py
fanstatic/tests/test_registry.py
fanstatic/tests/test_slot.py
fanstatic/tests/test_topbottominjector.py
fanstatic/tests/test_wsgi.py
fanstatic-1.6.dist-info/LICENSE.txt
fanstatic-1.6.dist-info/METADATA
fanstatic-1.6.dist-info/WHEEL
fanstatic-1.6.dist-info/entry_points.txt
fanstatic-1.6.dist-info/top_level.txt
fanstatic-1.6.dist-info/RECORD
