Metadata-Version: 2.1
Name: fanstatic
Version: 1.6
Summary: Flexible static resources for web applications
Home-page: https://www.fanstatic.org
Author: Fanstatic Developers
Author-email: zope-dev@zope.dev
License: BSD
Classifier: Topic :: Internet :: WWW/HTTP :: Dynamic Content
Classifier: Topic :: Internet :: WWW/HTTP :: WSGI :: Middleware
Classifier: Intended Audience :: Developers
Classifier: License :: OSI Approved :: BSD License
Classifier: Programming Language :: Python :: 3
Classifier: Programming Language :: Python :: 3.9
Classifier: Programming Language :: Python :: 3.10
Classifier: Programming Language :: Python :: 3.11
Classifier: Programming Language :: Python :: 3.12
Classifier: Programming Language :: Python :: 3.13
Classifier: Development Status :: 5 - Production/Stable
Requires-Python: >=3.9
License-File: LICENSE.txt
Requires-Dist: WebOb>=1.2
Requires-Dist: packaging
Requires-Dist: setuptools
Provides-Extra: closure
Requires-Dist: closure; extra == "closure"
Provides-Extra: cssmin
Requires-Dist: cssmin; extra == "cssmin"
Provides-Extra: jsmin
Requires-Dist: jsmin; extra == "jsmin"
Provides-Extra: test
Requires-Dist: closure; extra == "test"
Requires-Dist: cssmin; extra == "test"
Requires-Dist: jsmin; extra == "test"
Requires-Dist: pytest>=2.3; extra == "test"
Provides-Extra: docs
Requires-Dist: Sphinx; extra == "docs"
